geopandas/__init__.py
geopandas/_compat.py
geopandas/_config.py
geopandas/_decorator.py
geopandas/_version.py
geopandas/array.py
geopandas/base.py
geopandas/conftest.py
geopandas/explore.py
geopandas/geodataframe.py
geopandas/geoseries.py
geopandas/plotting.py
geopandas/sindex.py
geopandas/testing.py
geopandas/datasets/__init__.py
geopandas/io/__init__.py
geopandas/io/_geoarrow.py
geopandas/io/_pyarrow_hotfix.py
geopandas/io/arrow.py
geopandas/io/file.py
geopandas/io/sql.py
geopandas/io/util.py
geopandas/io/tests/__init__.py
geopandas/io/tests/generate_legacy_storage_files.py
geopandas/io/tests/test_arrow.py
geopandas/io/tests/test_file.py
geopandas/io/tests/test_file_geom_types_drivers.py
geopandas/io/tests/test_geoarrow.py
geopandas/io/tests/test_infer_schema.py
geopandas/io/tests/test_pickle.py
geopandas/io/tests/test_sql.py
geopandas/tests/__init__.py
geopandas/tests/test_api.py
geopandas/tests/test_array.py
geopandas/tests/test_compat.py
geopandas/tests/test_config.py
geopandas/tests/test_crs.py
geopandas/tests/test_datasets.py
geopandas/tests/test_decorator.py
geopandas/tests/test_dissolve.py
geopandas/tests/test_explore.py
geopandas/tests/test_extension_array.py
geopandas/tests/test_geocode.py
geopandas/tests/test_geodataframe.py
geopandas/tests/test_geom_methods.py
geopandas/tests/test_geoseries.py
geopandas/tests/test_merge.py
geopandas/tests/test_op_output_types.py
geopandas/tests/test_overlay.py
geopandas/tests/test_pandas_methods.py
geopandas/tests/test_plotting.py
geopandas/tests/test_show_versions.py
geopandas/tests/test_sindex.py
geopandas/tests/test_testing.py
geopandas/tests/test_types.py
geopandas/tests/util.py
geopandas/tests/data/null_geom.geojson
geopandas/tools/__init__.py
geopandas/tools/_random.py
geopandas/tools/_show_versions.py
geopandas/tools/clip.py
geopandas/tools/geocoding.py
geopandas/tools/hilbert_curve.py
geopandas/tools/overlay.py
geopandas/tools/sjoin.py
geopandas/tools/util.py
geopandas/tools/tests/__init__.py
geopandas-1.0.0.dist-info/LICENSE.txt
geopandas-1.0.0.dist-info/METADATA
geopandas-1.0.0.dist-info/WHEEL
geopandas-1.0.0.dist-info/top_level.txt
geopandas-1.0.0.dist-info/RECORD
